kernel_scilab/__init__.py
kernel_scilab/__main__.py
kernel_scilab/check.py
kernel_scilab/kernel.py
kernel_scilab/test.py
kernel_scilab/data/_make_figures.sci
kernel_scilab/data/kernel.json
kernel_scilab/data/logo-32x32.png
kernel_scilab/data/logo-64x64.png
kernel_scilab-1.0.3.data/data/share/jupyter/kernels/kernel_scilab/kernel.json
kernel_scilab-1.0.3.data/data/share/jupyter/kernels/kernel_scilab/logo-32x32.png
kernel_scilab-1.0.3.data/data/share/jupyter/kernels/kernel_scilab/logo-64x64.png
kernel_scilab-1.0.3.dist-info/LICENSE.txt
kernel_scilab-1.0.3.dist-info/METADATA
kernel_scilab-1.0.3.dist-info/WHEEL
kernel_scilab-1.0.3.dist-info/top_level.txt
kernel_scilab-1.0.3.dist-info/RECORD
